COPYING
MANIFEST.in
README.rst
example.py
setup.py
version.txt
ykpers.py
ykpers_cffi.egg-info/PKG-INFO
ykpers_cffi.egg-info/SOURCES.txt
ykpers_cffi.egg-info/dependency_links.txt
ykpers_cffi.egg-info/requires.txt
ykpers_cffi.egg-info/top_level.txt