Metadata-Version: 1.1
Name: ykpers-cffi
Version: 0.13.0.0a2
Summary: libykpers bindings for python via cffi
Home-page: https://github.com/habnabit/ykpers-cffi
Author: Aaron Gallagher
Author-email: _@habnab.it
License: ISC
Platform: UNKNOWN
Classifier: Development Status :: 3 - Alpha
Classifier: Intended Audience :: Developers
Classifier: License :: OSI Approved :: ISC License (ISCL)
Classifier: Operating System :: OS Independent
Classifier: Programming Language :: Python :: 2
Classifier: Topic :: Security
Classifier: Topic :: Utilities
